kitty/__init__.py
kitty/cli.py
kitty/core/__init__.py
kitty/core/logger.py
kitty/core/utils.py
kitty/templates/ai/README.md
kitty/templates/ai/requirements.txt
kitty/templates/ai/config/.gitkeep
kitty/templates/ai/models_saved/.gitkeep
kitty/templates/ai/notebooks/experiments.ipynb
kitty/templates/ai/src/data/loader.py
kitty/templates/ai/src/inference/predict.py
kitty/templates/ai/src/models/base_model.py
kitty/templates/ai/src/training/train.py
kitty/templates/automation/README.md
kitty/templates/automation/main.py
kitty/templates/automation/requirements.txt
kitty/templates/automation/config/.gitkeep
kitty/templates/automation/logs/.gitkeep
kitty/templates/automation/modules/.gitkeep
kitty/templates/automation/utils/helpers.py
kitty/templates/backend/.env.example
kitty/templates/backend/README.md
kitty/templates/backend/requirements.txt
kitty/templates/backend/src/app/main.py
kitty/templates/backend/src/app/api/routes.py
kitty/templates/backend/src/app/core/config.py
kitty/templates/backend/src/app/models/item.py
kitty/templates/backend/src/app/services/item_service.py
kitty/templates/backend/tests/test_api.py
kitty/templates/ds/README.md
kitty/templates/ds/requirements.txt
kitty/templates/ds/data/interim/.gitkeep
kitty/templates/ds/data/processed/.gitkeep
kitty/templates/ds/data/raw/.gitkeep
kitty/templates/ds/notebooks/01_eda.ipynb
kitty/templates/ds/notebooks/02_features.ipynb
kitty/templates/ds/notebooks/03_modeling.ipynb
kitty/templates/ds/reports/figures/.gitkeep
kitty/templates/ds/src/data_loader.py
kitty/templates/ds/src/evaluate.py
kitty/templates/ds/src/features.py
kitty/templates/ds/src/preprocessing.py
kitty/templates/ds/src/train.py
kitty/templates/research/README.md
kitty/templates/research/requirements.txt
kitty/templates/research/data/.gitkeep
kitty/templates/research/experiments/.gitkeep
kitty/templates/research/notebooks/research.ipynb
kitty/templates/research/paper/.gitkeep
kitty/templates/research/references/.gitkeep
kitty_scaffold-0.1.2.dist-info/licenses/LICENSE
kitty_scaffold-0.1.2.dist-info/METADATA
kitty_scaffold-0.1.2.dist-info/WHEEL
kitty_scaffold-0.1.2.dist-info/entry_points.txt
kitty_scaffold-0.1.2.dist-info/top_level.txt
kitty_scaffold-0.1.2.dist-info/RECORD
