Metadata-Version: 2.4
Name: kitty-scaffold
Version: 0.1.2
Summary: A professional project scaffolding tool for Python developers - quickly bootstrap AI, Data Science, Research, and Backend projects
Author-email: Bisal Prasad <bisalprasad2003@gmail.com>
License: MIT
Project-URL: Homepage, https://github.com/bisal2003/Python_kitty
Project-URL: Documentation, https://github.com/bisal2003/Python_kitty#readme
Project-URL: Repository, https://github.com/bisal2003/Python_kitty
Project-URL: Issues, https://github.com/bisal2003/Python_kitty/issues
Keywords: scaffolding,project-template,cli,data-science,ai,backend,automation,boilerplate
Classifier: Development Status :: 3 - Alpha
Classifier: Intended Audience :: Developers
Classifier: Topic :: Software Development :: Code Generators
Classifier: License :: OSI Approved :: MIT License
Classifier: Programming Language :: Python :: 3
Classifier: Programming Language :: Python :: 3.8
Classifier: Programming Language :: Python :: 3.9
Classifier: Programming Language :: Python :: 3.10
Classifier: Programming Language :: Python :: 3.11
Classifier: Programming Language :: Python :: 3.12
Requires-Python: >=3.8
License-File: LICENSE
Dynamic: license-file
